biobb_structure_utils/__init__.py
biobb_structure_utils/py.typed
biobb_structure_utils/gro_lib/__init__.py
biobb_structure_utils/gro_lib/gro.py
biobb_structure_utils/test/__init__.py
biobb_structure_utils/utils/__init__.py
biobb_structure_utils/utils/cat_pdb.py
biobb_structure_utils/utils/closest_residues.py
biobb_structure_utils/utils/common.py
biobb_structure_utils/utils/extract_atoms.py
biobb_structure_utils/utils/extract_chain.py
biobb_structure_utils/utils/extract_heteroatoms.py
biobb_structure_utils/utils/extract_model.py
biobb_structure_utils/utils/extract_molecule.py
biobb_structure_utils/utils/extract_residues.py
biobb_structure_utils/utils/remove_ligand.py
biobb_structure_utils/utils/remove_molecules.py
biobb_structure_utils/utils/remove_pdb_water.py
biobb_structure_utils/utils/renumber_structure.py
biobb_structure_utils/utils/sort_gro_residues.py
biobb_structure_utils/utils/str_check_add_hydrogens.py
biobb_structure_utils/utils/structure_check.py
biobb_structure_utils-5.1.0.dist-info/LICENSE
biobb_structure_utils-5.1.0.dist-info/METADATA
biobb_structure_utils-5.1.0.dist-info/WHEEL
biobb_structure_utils-5.1.0.dist-info/entry_points.txt
biobb_structure_utils-5.1.0.dist-info/top_level.txt
biobb_structure_utils-5.1.0.dist-info/RECORD
