Metadata-Version: 2.1
Name: biobb-structure-utils
Version: 5.1.0
Summary: biobb_structure_utils is the Biobb module collection to perform basic manipulations on 3d structures.
Home-page: https://github.com/bioexcel/biobb_structure_utils
Author: Biobb developers
Author-email: pau.andrio@bsc.es
Project-URL: Documentation, http://biobb-structure-utils.readthedocs.io/en/latest/
Project-URL: Bioexcel, https://bioexcel.eu/
Keywords: Bioinformatics Workflows BioExcel Compatibility
Classifier: Development Status :: 5 - Production/Stable
Classifier: Programming Language :: Python :: 3.9
Classifier: License :: OSI Approved :: Apache Software License
Classifier: Operating System :: MacOS :: MacOS X
Classifier: Operating System :: POSIX
Classifier: Operating System :: Unix
Requires-Python: >=3.9
License-File: LICENSE
Requires-Dist: biobb-common ==5.1.0
Requires-Dist: biobb-structure-checking >=3.15.6
